[
    {
        "rk":1,
        "squad":"Liverpool",
        "mp":35,
        "w":25,
        "d":7,
        "l":3,
        "gf":81,
        "ga":35,
        "gd":46,
        "pts":82,
        "pts_mp":2.34,
        "xg":75.4,
        "xga":32.0,
        "xgd":43.4,
        "xgd_90":1.24,
        "last_5":"L W W W L",
        "attendance":60321,
        "top_team_scorer":"Mohamed Salah - 28",
        "goalkeeper":"Alisson",
        "notes":null,
        "season":"2024-2025",
        "fetched_date":"2025-05-05",
        "week_no":19
    },
    {
        "rk":2,
        "squad":"Arsenal",
        "mp":35,
        "w":18,
        "d":13,
        "l":4,
        "gf":64,
        "ga":31,
        "gd":33,
        "pts":67,
        "pts_mp":1.91,
        "xg":54.4,
        "xga":29.9,
        "xgd":24.5,
        "xgd_90":0.7,
        "last_5":"D D W D L",
        "attendance":60256,
        "top_team_scorer":"Kai Havertz - 9",
        "goalkeeper":"David Raya",
        "notes":null,
        "season":"2024-2025",
        "fetched_date":"2025-05-05",
        "week_no":19
    },
    {
        "rk":3,
        "squad":"Manchester City",
        "mp":35,
        "w":19,
        "d":7,
        "l":9,
        "gf":67,
        "ga":43,
        "gd":24,
        "pts":64,
        "pts_mp":1.83,
        "xg":61.9,
        "xga":45.2,
        "xgd":16.6,
        "xgd_90":0.48,
        "last_5":"D W W W W",
        "attendance":52741,
        "top_team_scorer":"Erling Haaland - 21",
        "goalkeeper":"Ederson",
        "notes":null,
        "season":"2024-2025",
        "fetched_date":"2025-05-05",
        "week_no":19
    },
    {
        "rk":4,
        "squad":"Newcastle United",
        "mp":35,
        "w":19,
        "d":6,
        "l":10,
        "gf":66,
        "ga":45,
        "gd":21,
        "pts":63,
        "pts_mp":1.8,
        "xg":59.5,
        "xga":43.1,
        "xgd":16.4,
        "xgd_90":0.47,
        "last_5":"W W L W D",
        "attendance":52182,
        "top_team_scorer":"Alexander Isak - 23",
        "goalkeeper":"Nick Pope",
        "notes":null,
        "season":"2024-2025",
        "fetched_date":"2025-05-05",
        "week_no":19
    },
    {
        "rk":5,
        "squad":"Chelsea",
        "mp":35,
        "w":18,
        "d":9,
        "l":8,
        "gf":62,
        "ga":41,
        "gd":21,
        "pts":63,
        "pts_mp":1.8,
        "xg":65.2,
        "xga":44.3,
        "xgd":21.0,
        "xgd_90":0.6,
        "last_5":"D D W W W",
        "attendance":39652,
        "top_team_scorer":"Cole Palmer - 15",
        "goalkeeper":"Robert S\u00e1nchez",
        "notes":null,
        "season":"2024-2025",
        "fetched_date":"2025-05-05",
        "week_no":19
    },
    {
        "rk":6,
        "squad":"Nottingham Forest",
        "mp":34,
        "w":18,
        "d":6,
        "l":10,
        "gf":53,
        "ga":41,
        "gd":12,
        "pts":60,
        "pts_mp":1.76,
        "xg":40.4,
        "xga":43.4,
        "xgd":-3.0,
        "xgd_90":-0.09,
        "last_5":"W L L W L",
        "attendance":30036,
        "top_team_scorer":"Chris Wood - 19",
        "goalkeeper":"Matz Sels",
        "notes":null,
        "season":"2024-2025",
        "fetched_date":"2025-05-05",
        "week_no":19
    },
    {
        "rk":7,
        "squad":"Aston Villa",
        "mp":35,
        "w":17,
        "d":9,
        "l":9,
        "gf":55,
        "ga":49,
        "gd":6,
        "pts":60,
        "pts_mp":1.71,
        "xg":53.3,
        "xga":45.9,
        "xgd":7.4,
        "xgd_90":0.21,
        "last_5":"W W W L W",
        "attendance":42070,
        "top_team_scorer":"Ollie Watkins - 15",
        "goalkeeper":"Emiliano Mart\u00ednez",
        "notes":null,
        "season":"2024-2025",
        "fetched_date":"2025-05-05",
        "week_no":19
    },
    {
        "rk":8,
        "squad":"Bournemouth",
        "mp":35,
        "w":14,
        "d":11,
        "l":10,
        "gf":55,
        "ga":42,
        "gd":13,
        "pts":53,
        "pts_mp":1.51,
        "xg":60.5,
        "xga":45.7,
        "xgd":14.8,
        "xgd_90":0.42,
        "last_5":"D W D D W",
        "attendance":11210,
        "top_team_scorer":"Justin Kluivert - 12",
        "goalkeeper":"Kepa Arrizabalaga",
        "notes":null,
        "season":"2024-2025",
        "fetched_date":"2025-05-05",
        "week_no":19
    },
    {
        "rk":9,
        "squad":"Brentford",
        "mp":35,
        "w":15,
        "d":7,
        "l":13,
        "gf":62,
        "ga":53,
        "gd":9,
        "pts":52,
        "pts_mp":1.49,
        "xg":53.7,
        "xga":52.5,
        "xgd":1.2,
        "xgd_90":0.03,
        "last_5":"D D W W W",
        "attendance":18832,
        "top_team_scorer":"Yoane Wissa, Bryan Mbeumo - 18",
        "goalkeeper":"Mark Flekken",
        "notes":null,
        "season":"2024-2025",
        "fetched_date":"2025-05-05",
        "week_no":19
    },
    {
        "rk":10,
        "squad":"Brighton",
        "mp":35,
        "w":13,
        "d":13,
        "l":9,
        "gf":57,
        "ga":56,
        "gd":1,
        "pts":52,
        "pts_mp":1.49,
        "xg":52.7,
        "xga":49.4,
        "xgd":3.3,
        "xgd_90":0.1,
        "last_5":"L D L W D",
        "attendance":31808,
        "top_team_scorer":"Jo\u00e3o Pedro - 10",
        "goalkeeper":"Bart Verbruggen",
        "notes":null,
        "season":"2024-2025",
        "fetched_date":"2025-05-05",
        "week_no":19
    },
    {
        "rk":11,
        "squad":"Fulham",
        "mp":35,
        "w":14,
        "d":9,
        "l":12,
        "gf":50,
        "ga":47,
        "gd":3,
        "pts":51,
        "pts_mp":1.46,
        "xg":46.0,
        "xga":40.6,
        "xgd":5.4,
        "xgd_90":0.15,
        "last_5":"W L L W L",
        "attendance":26727,
        "top_team_scorer":"Ra\u00fal Jim\u00e9nez - 10",
        "goalkeeper":"Bernd Leno",
        "notes":null,
        "season":"2024-2025",
        "fetched_date":"2025-05-05",
        "week_no":19
    },
    {
        "rk":12,
        "squad":"Crystal Palace",
        "mp":34,
        "w":11,
        "d":12,
        "l":11,
        "gf":43,
        "ga":47,
        "gd":-4,
        "pts":45,
        "pts_mp":1.32,
        "xg":51.3,
        "xga":44.2,
        "xgd":7.2,
        "xgd_90":0.21,
        "last_5":"W L L D D",
        "attendance":25080,
        "top_team_scorer":"Jean-Philippe Mateta - 14",
        "goalkeeper":"Dean Henderson",
        "notes":null,
        "season":"2024-2025",
        "fetched_date":"2025-05-05",
        "week_no":19
    },
    {
        "rk":13,
        "squad":"Wolves",
        "mp":35,
        "w":12,
        "d":5,
        "l":18,
        "gf":51,
        "ga":62,
        "gd":-11,
        "pts":41,
        "pts_mp":1.17,
        "xg":40.4,
        "xga":53.5,
        "xgd":-13.1,
        "xgd_90":-0.37,
        "last_5":"W W W W L",
        "attendance":30621,
        "top_team_scorer":"Matheus Cunha - 15",
        "goalkeeper":"Jos\u00e9 S\u00e1",
        "notes":null,
        "season":"2024-2025",
        "fetched_date":"2025-05-05",
        "week_no":19
    },
    {
        "rk":14,
        "squad":"Everton",
        "mp":35,
        "w":8,
        "d":15,
        "l":12,
        "gf":36,
        "ga":43,
        "gd":-7,
        "pts":39,
        "pts_mp":1.11,
        "xg":36.9,
        "xga":43.1,
        "xgd":-6.2,
        "xgd_90":-0.18,
        "last_5":"D W L L D",
        "attendance":38397,
        "top_team_scorer":"Iliman Ndiaye, Beto - 7",
        "goalkeeper":"Jordan Pickford",
        "notes":null,
        "season":"2024-2025",
        "fetched_date":"2025-05-05",
        "week_no":19
    },
    {
        "rk":15,
        "squad":"Manchester United",
        "mp":35,
        "w":10,
        "d":9,
        "l":16,
        "gf":42,
        "ga":51,
        "gd":-9,
        "pts":39,
        "pts_mp":1.11,
        "xg":47.2,
        "xga":50.9,
        "xgd":-3.7,
        "xgd_90":-0.11,
        "last_5":"D L L D L",
        "attendance":73738,
        "top_team_scorer":"Bruno Fernandes - 8",
        "goalkeeper":"Andr\u00e9 Onana",
        "notes":null,
        "season":"2024-2025",
        "fetched_date":"2025-05-05",
        "week_no":19
    },
    {
        "rk":16,
        "squad":"Tottenham",
        "mp":35,
        "w":11,
        "d":5,
        "l":19,
        "gf":63,
        "ga":57,
        "gd":6,
        "pts":38,
        "pts_mp":1.09,
        "xg":55.6,
        "xga":56.4,
        "xgd":-0.8,
        "xgd_90":-0.02,
        "last_5":"W L L L D",
        "attendance":61159,
        "top_team_scorer":"Brennan Johnson - 11",
        "goalkeeper":"Guglielmo Vicario",
        "notes":null,
        "season":"2024-2025",
        "fetched_date":"2025-05-05",
        "week_no":19
    },
    {
        "rk":17,
        "squad":"West Ham",
        "mp":35,
        "w":9,
        "d":10,
        "l":16,
        "gf":40,
        "ga":59,
        "gd":-19,
        "pts":37,
        "pts_mp":1.06,
        "xg":43.1,
        "xga":54.9,
        "xgd":-11.8,
        "xgd_90":-0.34,
        "last_5":"D L D L D",
        "attendance":62463,
        "top_team_scorer":"Jarrod Bowen - 10",
        "goalkeeper":"Alphonse Areola",
        "notes":null,
        "season":"2024-2025",
        "fetched_date":"2025-05-05",
        "week_no":19
    },
    {
        "rk":18,
        "squad":"Ipswich Town",
        "mp":35,
        "w":4,
        "d":10,
        "l":21,
        "gf":35,
        "ga":76,
        "gd":-41,
        "pts":22,
        "pts_mp":0.63,
        "xg":31.3,
        "xga":69.4,
        "xgd":-38.1,
        "xgd_90":-1.09,
        "last_5":"L D L L D",
        "attendance":29753,
        "top_team_scorer":"Liam Delap - 12",
        "goalkeeper":"Arijanet Muric",
        "notes":null,
        "season":"2024-2025",
        "fetched_date":"2025-05-05",
        "week_no":19
    },
    {
        "rk":19,
        "squad":"Leicester City",
        "mp":35,
        "w":5,
        "d":6,
        "l":24,
        "gf":29,
        "ga":76,
        "gd":-47,
        "pts":21,
        "pts_mp":0.6,
        "xg":30.5,
        "xga":67.6,
        "xgd":-37.1,
        "xgd_90":-1.06,
        "last_5":"L D L L W",
        "attendance":31418,
        "top_team_scorer":"Jamie Vardy - 8",
        "goalkeeper":"Mads Hermansen",
        "notes":null,
        "season":"2024-2025",
        "fetched_date":"2025-05-05",
        "week_no":19
    },
    {
        "rk":20,
        "squad":"Southampton",
        "mp":35,
        "w":2,
        "d":5,
        "l":28,
        "gf":25,
        "ga":82,
        "gd":-57,
        "pts":11,
        "pts_mp":0.31,
        "xg":30.7,
        "xga":78.1,
        "xgd":-47.3,
        "xgd_90":-1.35,
        "last_5":"L L D L L",
        "attendance":30854,
        "top_team_scorer":"Paul Onuachu - 4",
        "goalkeeper":"Aaron Ramsdale",
        "notes":null,
        "season":"2024-2025",
        "fetched_date":"2025-05-05",
        "week_no":19
    }
]